.gitignore
README.rst
bootstrap.py
buildout.cfg
setup.cfg
setup.py
docs/HISTORY.txt
docs/INSTALL.txt
docs/LICENSE.GPL
docs/LICENSE.txt
transmogrify/__init__.py
transmogrify.webcrawler.egg-info/PKG-INFO
transmogrify.webcrawler.egg-info/SOURCES.txt
transmogrify.webcrawler.egg-info/dependency_links.txt
transmogrify.webcrawler.egg-info/entry_points.txt
transmogrify.webcrawler.egg-info/namespace_packages.txt
transmogrify.webcrawler.egg-info/not-zip-safe
transmogrify.webcrawler.egg-info/requires.txt
transmogrify.webcrawler.egg-info/top_level.txt
transmogrify/webcrawler/__init__.py
transmogrify/webcrawler/configure.zcml
transmogrify/webcrawler/staticcreator.py
transmogrify/webcrawler/staticcreator.txt
transmogrify/webcrawler/tests.py
transmogrify/webcrawler/testsites.txt
transmogrify/webcrawler/typerecognitor.py
transmogrify/webcrawler/typerecognitor.txt
transmogrify/webcrawler/webcrawler.py
transmogrify/webcrawler/webcrawler.txt
transmogrify/webcrawler/external/__init__.py
transmogrify/webcrawler/external/relative_url.py
transmogrify/webcrawler/external/webchecker.py
transmogrify/webcrawler/external/websucker.py
transmogrify/webcrawler/test_staticsite/cia-plone-view-source.jpg
transmogrify/webcrawler/test_staticsite/egenius-plone.gif
transmogrify/webcrawler/test_staticsite/file.doc
transmogrify/webcrawler/test_staticsite/file1.htm
transmogrify/webcrawler/test_staticsite/file2.htm
transmogrify/webcrawler/test_staticsite/file3.html
transmogrify/webcrawler/test_staticsite/file4.HTML
transmogrify/webcrawler/test_staticsite/plone_schema.png
transmogrify/webcrawler/test_staticsite/subfolder/subfile1.htm
transmogrify/webcrawler/test_staticsite/subfolder2/subfile1.htm
transmogrify/webcrawler/webstemmer/Makefile
transmogrify/webcrawler/webstemmer/README.txt
transmogrify/webcrawler/webstemmer/__init__.py
transmogrify/webcrawler/webstemmer/analyze.py
transmogrify/webcrawler/webstemmer/extract.py
transmogrify/webcrawler/webstemmer/gzipstream.py
transmogrify/webcrawler/webstemmer/html2txt.py
transmogrify/webcrawler/webstemmer/htmldom.py
transmogrify/webcrawler/webstemmer/htmlparser3.py
transmogrify/webcrawler/webstemmer/htmlutils.py
transmogrify/webcrawler/webstemmer/httplib.py
transmogrify/webcrawler/webstemmer/layoutils.py
transmogrify/webcrawler/webstemmer/perf.py
transmogrify/webcrawler/webstemmer/sgmlparser3.py
transmogrify/webcrawler/webstemmer/style.py
