Metadata-Version: 1.0
Name: transmogrify.webcrawler
Version: 1.2.1
Summary: Crawling and feeding html content into a transmogrifier pipeline
Home-page: http://github.com/collective/transmogrify.webcrawler
Author: Dylan Jay
Author-email: software@pretaweb.com
License: GPL
Keywords: transmogrifier blueprint funnelweb source plone import conversion microsoft office
Platform: UNKNOWN
Classifier: Programming Language :: Python
Classifier: Topic :: Software Development :: Libraries :: Python Modules
